[{"keyword": "TES LNG", "show_name": "TES LNG"}, {"keyword": "EDG WBG", "show_name": "EDG战胜WBG"}, {"keyword": "周星驰喊话周杰伦", "show_name": "周星驰喊话周杰伦"}, {"keyword": "黄婷婷仅查出9万资产", "show_name": "黄婷婷仅查出9万资产"}, {"keyword": "森林之子改成1万天后", "show_name": "森林之子改成1万天后"}, {"keyword": "周杰伦粉丝2055年现状", "show_name": "周杰伦粉丝2055年现状"}, {"keyword": "建议降低教育水平在积分落户比例", "show_name": "建议降低教育水平在积分落户比例"}, {"keyword": "龙珠电光火石4发布现场", "show_name": "龙珠电光火石4发布现场"}, {"keyword": "国家电影局召开球2座谈会", "show_name": "国家电影局召开球2座谈会"}, {"keyword": "世界民族音乐有何特别", "show_name": "世界民族音乐有何特别"}, {"keyword": "精减中央国家机关人员编制", "show_name": "精减中央国家机关人员编制"}, {"keyword": "锐评RNG战BLG比赛", "show_name": "锐评RNG战BLG比赛"}, {"keyword": "骆歆发文祝福记得", "show_name": "骆歆发文祝福记得"}, {"keyword": "被戴因折磨的米将军", "show_name": "被戴因折磨的米将军"}, {"keyword": "P社首次发行国产游戏", "show_name": "P社首次发行国产游戏"}, {"keyword": "明日方舟干员练度推荐", "show_name": "明日方舟干员练度推荐"}, {"keyword": "13岁男孩身高1米91", "show_name": "13岁男孩身高1米91"}, {"keyword": "Uzi枣间新闻", "show_name": "Uzi枣间新闻"}, {"keyword": "一个211师范生的前30年", "show_name": "一个211师范生的前30年"}, {"keyword": "原神魔女的茶会剧情PV", "show_name": "原神魔女的茶会剧情PV"}, {"keyword": "LOL手游体验服派克打野", "show_name": "LOL手游体验服派克打野"}, {"keyword": "加料300元的螺蛳粉", "show_name": "加料300元的螺蛳粉"}, {"keyword": "天气这么热还用春捂吗", "show_name": "天气这么热还用春捂吗"}, {"keyword": "DOTA2绝命孽海套装预览", "show_name": "DOTA2绝命孽海套装预览"}, {"keyword": "男女生表达爱意的区别", "show_name": "男女生表达爱意的区别"}, {"keyword": "芝顿是什么梗", "show_name": "芝顿是什么梗"}, {"keyword": "黑化靠演技不是靠眼影", "show_name": "黑化靠演技不是靠眼影"}, {"keyword": "球2又夺票房日冠", "show_name": "球2又夺票房日冠"}, {"keyword": "云顶S8.5棋子神郭嘉", "show_name": "云顶S8.5棋子神郭嘉"}, {"keyword": "林心如网飞犯罪新片PV", "show_name": "林心如网飞犯罪新片PV"}]