[{"keyword": "猴子时隔两年再登KPL", "show_name": "猴子时隔两年再登KPL"}, {"keyword": "FPX RA", "show_name": "FPX RA"}, {"keyword": "浙江选育出螺蛳粉味樱花", "show_name": "浙江选育出螺蛳粉味樱花"}, {"keyword": "丁薛祥何立峰张国清刘国中为副总理", "show_name": "丁薛祥何立峰张国清刘国中为副总理"}, {"keyword": "恩佐一场比赛打出身价", "show_name": "恩佐一场比赛打出身价"}, {"keyword": "妍珍在监狱里播报天气", "show_name": "妍珍在监狱里播报天气"}, {"keyword": "圆明园通报游客攀爬遗址", "show_name": "圆明园通报游客攀爬遗址"}, {"keyword": "中国队世锦赛5000米接力夺冠", "show_name": "中国队世锦赛5000米接力夺冠"}, {"keyword": "一只大哈鱼", "show_name": "一只大哈鱼被甲方拉黑"}, {"keyword": "400块切半个毛肚涮火锅", "show_name": "400块切半个毛肚涮火锅"}, {"keyword": "鉴定嘉陵江边疑似恐龙化石", "show_name": "鉴定嘉陵江边疑似恐龙化石"}, {"keyword": "瞬息全宇宙影史获奖最多", "show_name": "瞬息全宇宙影史获奖最多"}, {"keyword": "数学专业毕业9年现状", "show_name": "数学专业毕业9年现状"}, {"keyword": "四六级答案", "show_name": "四六级答案"}, {"keyword": "世界上最孤独的鲸去世", "show_name": "世界上最孤独的鲸去世"}, {"keyword": "数字生命为何无法实现", "show_name": "数字生命为何无法实现"}, {"keyword": "23年前主角必死的游戏", "show_name": "23年前主角必死的游戏"}, {"keyword": "AL EDG", "show_name": "EDG战胜AL"}, {"keyword": "柯南重要主线海猿岛预告", "show_name": "柯南重要主线海猿岛预告"}, {"keyword": "向鹏2比3张本智和", "show_name": "向鹏2比3张本智和"}, {"keyword": "林孝埈1000米被撞", "show_name": "林孝埈1000米被撞"}, {"keyword": "COD16上架steam后现状", "show_name": "COD16上架steam后现状"}, {"keyword": "樱花人像姿势引导教学", "show_name": "樱花人像姿势引导教学"}, {"keyword": "王者多款典藏皮肤优化", "show_name": "王者多款典藏皮肤优化"}, {"keyword": "极客湾测麒麟9000真实能效", "show_name": "极客湾测麒麟9000真实能效"}, {"keyword": "梗带走了我的名字", "show_name": "梗带走了我的名字"}, {"keyword": "体育总局局长谈振兴三大球", "show_name": "体育总局局长谈振兴三大球"}, {"keyword": "纸嫁衣3真人版电影", "show_name": "纸嫁衣3真人cos版电影"}, {"keyword": "春夏神裤", "show_name": "春夏神裤"}, {"keyword": "必胜客自助到底值不值", "show_name": "必胜客自助到底值不值"}]