[{"keyword": "TES RNG", "show_name": "TES RNG"}, {"keyword": "这就是中国国色", "show_name": "这就是中国国色"}, {"keyword": "184一盒的红烧牛肉面", "show_name": "184一盒的红烧牛肉面"}, {"keyword": "95后考研落榜父母双双上岸", "show_name": "95后考研落榜父母双双上岸"}, {"keyword": "梅西拒绝降薪续约", "show_name": "梅西拒绝降薪续约"}, {"keyword": "谁说丑男和美男只差BGM", "show_name": "谁说丑男和美男只差BGM"}, {"keyword": "WBG AL", "show_name": "WBG战胜AL"}, {"keyword": "IG Baolan冠军卡将亮相", "show_name": "IG Baolan冠军卡将亮相"}, {"keyword": "建议试行十二年义务教育", "show_name": "建议试行十二年义务教育"}, {"keyword": "高三女孩脱稿演讲燃爆全场", "show_name": "高三女孩脱稿演讲燃爆全场"}, {"keyword": "在B站和10万人上自习", "show_name": "在B站和10万人上自习"}, {"keyword": "1.2亿中国老人在失去听力", "show_name": "1.2亿中国老人在失去听力"}, {"keyword": "Switch厕纸游戏笑死了", "show_name": "Switch厕纸游戏笑死了"}, {"keyword": "进击的巨人", "show_name": "进击的巨人"}, {"keyword": "狂飙全剧最窒息饭局", "show_name": "狂飙全剧最窒息饭局"}, {"keyword": "王者新版无脑打野教学", "show_name": "王者新版无脑打野教学"}, {"keyword": "LOL猫咪重做后更强了", "show_name": "LOL猫咪重做后更强了"}, {"keyword": "UP主见完吴京见邓超", "show_name": "UP主见完吴京见邓超"}, {"keyword": "NiKo生于战火的最强步枪手", "show_name": "NiKo生于战火的最强步枪手"}, {"keyword": "黑色沙漠steam免费领取", "show_name": "黑色沙漠steam免费领取"}, {"keyword": "赛尔号最逆天BOSS", "show_name": "赛尔号最逆天BOSS"}, {"keyword": "23年最新口碑灾难爽片", "show_name": "23年最新口碑灾难爽片"}, {"keyword": "别对余华有什么误解", "show_name": "别对余华有什么误解"}, {"keyword": "EDG FoFo", "show_name": "EDG FoFo"}, {"keyword": "森林之子未实装内容", "show_name": "森林之子未实装内容"}, {"keyword": "65岁阿姨离婚后骑行世界", "show_name": "65岁阿姨离婚后骑行世界"}, {"keyword": "LOL英雄价格调整", "show_name": "LOL英雄价格调整"}, {"keyword": "moss智子婚礼现场", "show_name": "moss智子婚礼现场"}, {"keyword": "C罗带队逆转绝地求生", "show_name": "C罗带队逆转绝地求生"}, {"keyword": "忘川朱元璋预告视频", "show_name": "忘川朱元璋预告视频"}]